server/__init__.py
server/server_start.py
server/custom/__init__.py
server/custom/core.py
server/custom/decorators.py
server/custom/function.py
server/custom/metaclass.py
server/custom/parse_args.py
server/custom/variables.py
server/database/__init__.py
server/database/database.py
server/descriptors/__init__.py
server/descriptors/address.py
server/descriptors/port.py
server/gui/__init__.py
server/gui/add_user.py
server/gui/config_window.py
server/gui/del_user.py
server/gui/main_window.py
server/log/__init__.py
server/log/log_config.py
server/log/log_variables.py
Messenger_Desktop_Server_Application-0.7.dist-info/METADATA
Messenger_Desktop_Server_Application-0.7.dist-info/WHEEL
Messenger_Desktop_Server_Application-0.7.dist-info/top_level.txt
Messenger_Desktop_Server_Application-0.7.dist-info/RECORD
